nepse_data/__init__.py
nepse_data/src.py
nepal_stock_price-1.0.0.dist-info/LICENSE
nepal_stock_price-1.0.0.dist-info/METADATA
nepal_stock_price-1.0.0.dist-info/WHEEL
nepal_stock_price-1.0.0.dist-info/top_level.txt
nepal_stock_price-1.0.0.dist-info/RECORD
