Metadata-Version: 2.1
Name: nepal-stock-price
Version: 1.0.0
Summary: a python package for getting price history of companies listed in nepse
Home-page: https://github.com/keskhanal/nepse-data
Author: Keshav Khanal
Author-email: me.keskhanal@gmail.com
Classifier: Programming Language :: Python :: 3
Classifier: License :: OSI Approved :: MIT License
Classifier: Operating System :: OS Independent
Requires-Python: >=3.6
License-File: LICENSE
Requires-Dist: beautifulsoup4 (==4.11.1)
Requires-Dist: bs4 (==0.0.1)
Requires-Dist: Jinja2 (==3.1.2)
Requires-Dist: numpy (==1.23.1)
Requires-Dist: pandas (==1.4.3)
Requires-Dist: pycparser (==2.21)
Requires-Dist: pywin32 (==304)
Requires-Dist: requests (==2.28.1)
Requires-Dist: selenium (==4.3.0)
Requires-Dist: urllib3 (==1.26.11)
Requires-Dist: webdriver-manager (==3.8.3)
Requires-Dist: Werkzeug (==2.2.1)
Requires-Dist: zipp (==3.8.1)
